{
  "bitcoin": [
    [
      1782663119,
      59798.2
    ],
    [
      1782664020,
      59642.7
    ],
    [
      1782664922,
      59659.9
    ],
    [
      1782665823,
      59592.7
    ],
    [
      1782666725,
      59546.5
    ],
    [
      1782667626,
      59528.6
    ],
    [
      1782668528,
      59426.9
    ],
    [
      1782669429,
      59515.6
    ]
  ],
  "ethereum": [
    [
      1782663119,
      1577.41
    ],
    [
      1782664020,
      1572.1
    ],
    [
      1782664922,
      1568.22
    ],
    [
      1782665823,
      1568.99
    ],
    [
      1782666725,
      1568.0
    ],
    [
      1782667626,
      1565.84
    ],
    [
      1782668528,
      1565.85
    ],
    [
      1782669429,
      1570.35
    ]
  ],
  "avalanche-2": [
    [
      1782663119,
      6.3
    ],
    [
      1782664020,
      6.281
    ],
    [
      1782664922,
      6.28
    ],
    [
      1782665823,
      6.295
    ],
    [
      1782666725,
      6.306
    ],
    [
      1782667626,
      6.29
    ],
    [
      1782668528,
      6.29
    ],
    [
      1782669429,
      6.313
    ]
  ],
  "ondo-finance": [
    [
      1782663119,
      0.30831
    ],
    [
      1782664020,
      0.30761
    ],
    [
      1782664922,
      0.30734
    ],
    [
      1782665823,
      0.30775
    ],
    [
      1782666725,
      0.30771
    ],
    [
      1782667626,
      0.30735
    ],
    [
      1782668528,
      0.30584
    ],
    [
      1782669429,
      0.30708
    ]
  ],
  "binancecoin": [
    [
      1782652302,
      553.71
    ]
  ],
  "ripple": [
    [
      1782652302,
      1.046
    ]
  ],
  "solana": [
    [
      1782652302,
      71.34
    ]
  ],
  "dogecoin": [
    [
      1782652302,
      0.073356
    ]
  ],
  "cardano": [
    [
      1782652302,
      0.144129
    ]
  ],
  "tron": [
    [
      1782652302,
      0.32378
    ]
  ],
  "chainlink": [
    [
      1782652302,
      7.24
    ]
  ],
  "the-open-network": [
    [
      1782652302,
      1.55
    ]
  ],
  "stellar": [
    [
      1782652302,
      0.170718
    ]
  ],
  "hedera-hashgraph": [
    [
      1782652302,
      0.071119
    ]
  ],
  "sui": [
    [
      1782652302,
      0.683263
    ]
  ],
  "bitcoin-cash": [
    [
      1782652302,
      192.2
    ]
  ],
  "litecoin": [
    [
      1782652302,
      42.86
    ]
  ],
  "polkadot": [
    [
      1782652302,
      0.804932
    ]
  ],
  "hyperliquid": [
    [
      1782652302,
      62.56
    ]
  ],
  "monero": [
    [
      1782652302,
      311.63
    ]
  ],
  "_alerts_sent": {}
}