{
  "bitcoin": [
    [
      1783537953,
      62066
    ],
    [
      1783538622,
      62135
    ],
    [
      1783539749,
      62191
    ],
    [
      1783540946,
      62170
    ],
    [
      1783541847,
      62173
    ],
    [
      1783542749,
      62192
    ],
    [
      1783543650,
      62137
    ],
    [
      1783544553,
      62050
    ]
  ],
  "ethereum": [
    [
      1783537953,
      1733.47
    ],
    [
      1783538622,
      1734.9
    ],
    [
      1783539749,
      1737.81
    ],
    [
      1783540946,
      1736.53
    ],
    [
      1783541847,
      1735.76
    ],
    [
      1783542749,
      1737.47
    ],
    [
      1783543650,
      1736.11
    ],
    [
      1783544553,
      1734.61
    ]
  ],
  "avalanche-2": [
    [
      1783537953,
      6.44
    ],
    [
      1783538622,
      6.44
    ],
    [
      1783539749,
      6.45
    ],
    [
      1783540946,
      6.45
    ],
    [
      1783541847,
      6.44
    ],
    [
      1783542749,
      6.44
    ],
    [
      1783543650,
      6.43
    ],
    [
      1783544553,
      6.43
    ]
  ],
  "ondo-finance": [
    [
      1783537953,
      0.314772
    ],
    [
      1783538622,
      0.314699
    ],
    [
      1783539749,
      0.314801
    ],
    [
      1783540946,
      0.314528
    ],
    [
      1783541847,
      0.314766
    ],
    [
      1783542749,
      0.314873
    ],
    [
      1783543650,
      0.314465
    ],
    [
      1783544553,
      0.313607
    ]
  ],
  "binancecoin": [
    [
      1783537953,
      565.56
    ],
    [
      1783538622,
      565.73
    ],
    [
      1783539749,
      566.54
    ],
    [
      1783540946,
      566.14
    ],
    [
      1783541847,
      566.19
    ],
    [
      1783542749,
      566.32
    ],
    [
      1783543650,
      565.93
    ],
    [
      1783544553,
      565.73
    ]
  ],
  "ripple": [
    [
      1783537953,
      1.085
    ],
    [
      1783538622,
      1.086
    ],
    [
      1783539749,
      1.089
    ],
    [
      1783540946,
      1.09
    ],
    [
      1783541847,
      1.088
    ],
    [
      1783542749,
      1.089
    ],
    [
      1783543650,
      1.089
    ],
    [
      1783544553,
      1.088
    ]
  ],
  "solana": [
    [
      1783537953,
      76.99
    ],
    [
      1783538622,
      76.96
    ],
    [
      1783539749,
      77.2
    ],
    [
      1783540946,
      77.32
    ],
    [
      1783541847,
      77.37
    ],
    [
      1783542749,
      77.3
    ],
    [
      1783543650,
      77.09
    ],
    [
      1783544553,
      77.07
    ]
  ],
  "dogecoin": [
    [
      1783537953,
      0.072329
    ],
    [
      1783538622,
      0.072321
    ],
    [
      1783539749,
      0.072482
    ],
    [
      1783540946,
      0.072562
    ],
    [
      1783541847,
      0.07249
    ],
    [
      1783542749,
      0.072473
    ],
    [
      1783543650,
      0.07244
    ],
    [
      1783544553,
      0.072335
    ]
  ],
  "cardano": [
    [
      1783537953,
      0.166489
    ],
    [
      1783538622,
      0.16667
    ],
    [
      1783539749,
      0.166677
    ],
    [
      1783540946,
      0.166638
    ],
    [
      1783541847,
      0.166594
    ],
    [
      1783542749,
      0.166403
    ],
    [
      1783543650,
      0.166359
    ],
    [
      1783544553,
      0.165933
    ]
  ],
  "tron": [
    [
      1783537953,
      0.330091
    ],
    [
      1783538622,
      0.329786
    ],
    [
      1783539749,
      0.329843
    ],
    [
      1783540946,
      0.329814
    ],
    [
      1783541847,
      0.32975
    ],
    [
      1783542749,
      0.329705
    ],
    [
      1783543650,
      0.329467
    ],
    [
      1783544553,
      0.329498
    ]
  ],
  "chainlink": [
    [
      1783537953,
      7.62
    ],
    [
      1783538622,
      7.61
    ],
    [
      1783539749,
      7.63
    ],
    [
      1783540946,
      7.63
    ],
    [
      1783541847,
      7.63
    ],
    [
      1783542749,
      7.62
    ],
    [
      1783543650,
      7.61
    ],
    [
      1783544553,
      7.61
    ]
  ],
  "the-open-network": [
    [
      1783537953,
      1.58
    ],
    [
      1783538622,
      1.59
    ],
    [
      1783539749,
      1.59
    ],
    [
      1783540946,
      1.58
    ],
    [
      1783541847,
      1.58
    ],
    [
      1783542749,
      1.58
    ],
    [
      1783543650,
      1.58
    ],
    [
      1783544553,
      1.57
    ]
  ],
  "stellar": [
    [
      1783537953,
      0.181197
    ],
    [
      1783538622,
      0.181237
    ],
    [
      1783539749,
      0.181216
    ],
    [
      1783540946,
      0.181306
    ],
    [
      1783541847,
      0.181171
    ],
    [
      1783542749,
      0.18114
    ],
    [
      1783543650,
      0.180743
    ],
    [
      1783544553,
      0.180391
    ]
  ],
  "hedera-hashgraph": [
    [
      1783537953,
      0.069331
    ],
    [
      1783538622,
      0.069473
    ],
    [
      1783539749,
      0.06954
    ],
    [
      1783540946,
      0.069403
    ],
    [
      1783541847,
      0.069443
    ],
    [
      1783542749,
      0.069325
    ],
    [
      1783543650,
      0.06923
    ],
    [
      1783544553,
      0.069073
    ]
  ],
  "sui": [
    [
      1783537953,
      0.710028
    ],
    [
      1783538622,
      0.709773
    ],
    [
      1783539749,
      0.71138
    ],
    [
      1783540946,
      0.71128
    ],
    [
      1783541847,
      0.711241
    ],
    [
      1783542749,
      0.710854
    ],
    [
      1783543650,
      0.709433
    ],
    [
      1783544553,
      0.708299
    ]
  ],
  "bitcoin-cash": [
    [
      1783537953,
      233.79
    ],
    [
      1783538622,
      233.9
    ],
    [
      1783539749,
      234.24
    ],
    [
      1783540946,
      234.61
    ],
    [
      1783541847,
      234.21
    ],
    [
      1783542749,
      233.95
    ],
    [
      1783543650,
      233.34
    ],
    [
      1783544553,
      232.79
    ]
  ],
  "litecoin": [
    [
      1783537953,
      43.47
    ],
    [
      1783538622,
      43.36
    ],
    [
      1783539749,
      43.38
    ],
    [
      1783540946,
      43.39
    ],
    [
      1783541847,
      43.44
    ],
    [
      1783542749,
      43.41
    ],
    [
      1783543650,
      43.4
    ],
    [
      1783544553,
      43.33
    ]
  ],
  "polkadot": [
    [
      1783537953,
      0.825434
    ],
    [
      1783538622,
      0.824848
    ],
    [
      1783539749,
      0.825179
    ],
    [
      1783540946,
      0.824309
    ],
    [
      1783541847,
      0.824412
    ],
    [
      1783542749,
      0.823111
    ],
    [
      1783543650,
      0.822434
    ],
    [
      1783544553,
      0.821115
    ]
  ],
  "hyperliquid": [
    [
      1783537953,
      66.73
    ],
    [
      1783538622,
      66.89
    ],
    [
      1783539749,
      67.22
    ],
    [
      1783540946,
      67.19
    ],
    [
      1783541847,
      67.3
    ],
    [
      1783542749,
      67.21
    ],
    [
      1783543650,
      67.12
    ],
    [
      1783544553,
      66.88
    ]
  ],
  "monero": [
    [
      1783537953,
      321.77
    ],
    [
      1783538622,
      321.39
    ],
    [
      1783539749,
      321.25
    ],
    [
      1783540946,
      322.03
    ],
    [
      1783541847,
      322.1
    ],
    [
      1783542749,
      320.14
    ],
    [
      1783543650,
      318.63
    ],
    [
      1783544553,
      318.75
    ]
  ],
  "_alerts_sent": {}
}