{
  "75330": {
    "subject": "Pozor! Znížená cena",
    "sender": "Temu <temu@eu-shop.temuemail.com>",
    "body": "-----------------------------------------------------------------------\r\nTemu\r\n-----------------------------------------------------------------------\r\n\r\nTo properly view the full message content, please open this email in a high version mail client or browser.\r\n\r\nVisit this website to see our recommended products: https://app.temu.com/mbs_landing_goods.html?_bg_fs=1&_x_cid=textmail&_p_landing=1&_x_src=mail&msgid=180-20260702-03-B-1014623063398211586-100-L50PqrOW&locale_override=180~sk~EUR\r\n\r\n-----------------------------------------------------------------------\r\n\r\nUnsubscribe\r\nhttps://www.temu.com/bgms_unsubscribe_email.html?_p_landing=1&_x_src=mail1&_x_cid=textmail&_x_sid=unsubscribe&locale_exemption_scene=unsubscribe&msgid=180-20260702-03-B-1014623063398211586-100-L50PqrOW&locale_override=180~sk~EUR\r\n\r\nTerms & Conditions\r\nhttps://www.temu.com/terms-of-use.html?_p_landing=1&_x_src=mail&_x_cid=textmail\r\n\r\nPrivacy & Cookie Policy\r\nhttps://www.temu.com/bgp_private_policy.html?_p_landing=1&_x_src=mail&_x_cid=textmail\r\n\r\n-----------------------------------------------------------------------Váš tovar je teraz lacnejší! ͏ ‌     ­͏ ‌     ­͏ ‌     ­͏ ‌     ­͏ ‌     ­͏ ‌     ­͏ ‌     ­͏ ‌     ­͏ ‌     ­͏ ‌     ­͏ ‌     ­͏ ‌     ­͏ ‌     ­͏ ‌     ­͏ ‌     ­͏ ‌     ­͏ ‌     ­͏ ‌     ­͏ ‌     ­͏ ‌     ­͏ ‌     ­͏ ‌     ­͏ ‌     ­͏ ‌     ­͏ ‌     ­͏ ‌     ­͏ ‌     ­͏ ‌     ­͏ ‌     ­͏ ‌     ­͏ ‌     ­͏ ‌     ­͏ ‌     ­͏ ‌     ­͏ ‌     ­͏ ‌     ­͏ ‌     ­͏ ‌     ­͏ ‌     ­͏ ‌     ­͏ ‌     ­͏ ‌     ­͏ ‌     ­͏ ‌     ­͏ ‌     ­͏ ‌     ­͏ ‌     ­͏ ‌     ­͏ ‌     ­͏ ‌     ­͏ ‌     ­͏ ‌     ­͏ ‌     ­͏ ‌     ­͏ ‌     ­͏ ‌     ­͏ ‌     ­͏ ‌     ­͏ ‌     ­͏ ‌     ­͏ ‌     ­͏ ‌     ­͏ ‌     ­͏ ‌     ­͏ ‌     ­͏ ‌     ­͏ ‌     ­͏ ‌     ­͏ ‌     ­͏ ‌     ­͏ ‌     ­͏ ‌     ­͏ ‌     ­͏ ‌     ­͏ ‌     ­͏ ‌     ­͏ ‌     ­͏ ‌     ­͏ ‌     ­͏ ‌     ­͏ ‌     ­͏ ‌     ­͏ ‌     ­͏ ‌     ­͏ ‌     ­͏ ‌     ­͏ ‌     ­͏ ‌     ­͏ ‌     ­͏ ‌     ­͏ ‌     ­͏ ‌     ­͏ ‌     ­͏ ‌     ­͏ ‌     ­͏ ‌     ­͏ ‌     ­͏ ‌     ­͏ ‌     ­͏ ‌     ­͏ ‌     ­͏ ‌     ­͏ ‌     ­͏ ‌     ­͏ ‌     ­͏ ‌     ­͏ ‌     ­͏ ‌     ­͏ ‌     ­͏ ‌     ­͏ ‌     ­͏ ‌     ­͏ ‌     ­͏ ‌     ­͏ ‌     ­͏ ‌     ­͏ ‌     ­͏ ‌     ­͏ ‌     ­͏ ‌     ­͏ ‌     ­͏ ‌     ­͏ ‌     ­͏ ‌     ­͏ ‌     ­͏ ‌     ­͏ ‌     ­͏ ‌     ­͏ ‌     ­͏ ‌     ­͏ ‌     ­͏ ‌     ­͏ ‌     ­͏ ‌     ­͏ ‌     ­͏ ‌     ­͏ ‌     ­͏ ‌     ­͏ ‌     ­͏ ‌     ­͏ ‌     ­͏ ‌     ­͏ ‌     ­͏ ‌     ­͏ ‌     ­͏ ‌     ­͏ ‌     ­͏ ‌     ­͏ ‌     ­͏ ‌     ­͏ ‌     ­͏ ‌     ­͏ ‌     ­͏ ‌     ­͏ ‌     ­͏ ‌     ­͏ ‌     ­͏ ‌     ­͏ ‌     ­͏ ‌     ­͏ ‌     ­͏ ‌     ­͏ ‌     ­͏ ‌     ­͏ ‌     ­ Váš tovar je teraz lacnejší!  Na položky uvedené v tomto e-maile alebo v rámci tejto akcie, ktoré sú odosielané z krajín mimo EÚ, sa môžu vzťahovať colné poplatky.     Sledujte nás POZNÁMKA: Toto je automaticky vygenerovaný e-mail, neodpovedajte naň. Adresa kancelárie: First Floor, 25 St Stephens Green, Dublin 2, Ireland  Upozorňujeme, že na tejto adrese sa vrátenie tovaru nep"
  },
  "75329": {
    "subject": "Google Cloud Platform & APIs: платіж відхилено для домену 01FB74-1CEEDC-1297AD",
    "sender": "Google Payments <payments-noreply@google.com>",
    "body": "Google Cloud Platform & APIs\r\n\r\n\r\nВаша фінансова установа відхилила платіж із Вашого рахунку Mastercard  • •  \r\n• • 5159, зв’язаного з обліковим записом Google Cloud Platform & APIs, для  \r\nдомену 01FB74-1CEEDC-1297AD від 1 лип. 2026 р.. Указано таку причину:\r\nНа вашому рахунку недостатньо коштів для цієї трансакції.\r\n\r\nСервіс може працювати ще певний час. Проте щоб продовжити користуватися ним  \r\nу майбутньому, Вам потрібно зв’язатися зі своєю фінансовою установою та  \r\nвирішити проблему. Після цього оновіть дані про основний спосіб оплати та  \r\nсплатіть усі заборгованості.\r\n\r\nЩоб оновити або змінити основний спосіб оплати:\r\n\r\n  Увійдіть в обліковий запис Google Cloud Console  \r\n<https://auth.cloud.google/select-session?flow=unified&continueUrl=https://console.cloud.google/>.\r\n\r\n  Відкрийте Меню навігації консолі й виберіть Billing (Платежі).  Якщо у вас  \r\nкілька платіжних облікових записів Google Cloud, дотримуйтесь інструкцій  \r\nнижче.  Виберіть Go to linked billing account (Перейти до зв’язаного  \r\nплатіжного облікового запису), щоб керувати платежами Google Cloud для  \r\nпоточного проєкту.\r\n  Натисніть Manage billing accounts (Керувати платіжними обліковими  \r\nзаписами), щоб вибрати інший платіжний обліковий запис Google Cloud.\r\n\r\n\r\n\r\n\r\n\r\n------------------------------------------------------------------------------------\r\n\r\nДовідковий центр<https://support.google.com/cloud/#topic=6288636>\r\n\r\nЗв’язатися з  \r\nнами<https://support.google.com/cloud/contact/cloud_platform_billing>\r\n\r\nІдентифікатор клієнта Google Cloud Platform:  01FB74-1CEEDC-1297AD\r\nІдентифікатор платіжного профілю:  5477-1873-1527\r\n\r\nGoogle LLC 1600 Amphitheatre Parkway, Mountain View, CA 94043\r\n\r\nМи надіслали Вам це обов’язкове службове сповіщення, щоб повідомити про  \r\nважливі зміни в Google Cloud Platform & APIs або Вашому обліковому записі.\r\n\r\nGoogle\r\n\r\n  \t\r\n\r\n"
  },
  "75328": {
    "subject": "Action required: your billing account 01FB74-1CEEDC-1297AD is past\r\n due or has invalid payment information.",
    "sender": "\"Google Cloud Platform, Firebase, and APIs\" <CloudPlatform-noreply@google.com>",
    "body": "Google Cloud Platform Go to my console »\r\n\r\n\r\n\r\n\r\n\r\nAction required\r\n\r\n\r\nDear Google customer,\r\n\r\n\r\nYou are receiving this email because you are a Google Cloud Platform,  \r\nFirebase, or API customer.\r\n\r\n\r\nOur records indicate that your billing account: 01FB74-1CEEDC-1297AD is  \r\npast due or does not have valid payment information associated with it.  \r\nThis may happen if your credit card has expired or was cancelled, and we  \r\nhaven't received valid payment information from you.\r\n\r\nPlease update your billing account with valid payment information by  \r\nfollowing this link:\r\n\r\nhttps://console.cloud.google.com/billing/01FB74-1CEEDC-1297AD/settings\r\n\r\n\r\nFailure to make payments may result in suspension and/or termination of  \r\nyour billing account and the related Project(s) or Service(s). Note that  \r\nsome services might already be impacted. If you have already updated your  \r\npayment information, please disregard this message.\r\n\r\nIf you have any questions please contact us using this form:  \r\nhttps://support.google.com/code/contact/cloud_platform_billing\r\n\r\n\r\n\r\n\r\n\r\n\r\n\r\nThe Google team\r\n\r\n\r\n\r\n\r\n\r\nGoogle Plus Twitter Blogger\r\n\r\n\r\n\r\n© 2026 Google LLC, 1600 Amphitheatre Parkway, Mountain View, CA 94043\r\n\r\nYou have received this mandatory service announcement to update you about  \r\nimportant changes to Google Cloud Platform, Firebase, APIs, or to your  \r\naccount.\r\n\r\n\r\n\r\n"
  },
  "75304": {
    "subject": "POZVÁNKA",
    "sender": "BUKOVINA - MICHAELA BILÁ<michaela.bila@bukovinakosice.sk>",
    "body": "Dobrý deň naši snúbenci,\r\n\r\nrada by som Vás pozvala na osobné stretnutie pred Vašou svadobnou \r\nhostinou, ktorá sa bude konať u nás na Bukovine.\r\nRada by som s Vami prebrala detaily svadby, stretnutie, kde bude \r\nprítomná už aj moja koordinátorka spravidla trvá cca 1,5 hodinky, prosím \r\npripravte si dostatočné časové okno.\r\nVedeli by ste nám dať časový nástrel stretnutia, aby sme spoločne našli \r\nprienik v kalendároch?\r\nSme na Bukovine viac menej denne od cca 8.00 do 16.30 hod.\r\n\r\nĎakujem!\r\nS pozdravom\r\n-- \r\n\r\nMgr. Michaela Bilá\r\n\r\nHead manager Bukovina\r\n\r\n+421908 849 791\r\n\r\nwww.bukovinakosice.sk [1]\r\n\r\n\r\n\r\nLinks:\r\n------\r\n[1] http://www.bukovinakosice.sk"
  },
  "75256": {
    "subject": "Immediate Action Required on 878341164164",
    "sender": "google-cloud-compliance@google.com",
    "body": "We have detected potentially compromised Service Account credentials  \r\nassociated with your Google Cloud Platform account.\r\n\r\n\r\n\r\n\r\nGoogle Cloud Platform\r\n\r\n\r\n\r\nMY CONSOLE\r\n\r\n\r\n\r\n\r\nNotification Suspicious Activity Alert\r\n\r\n\r\n\r\nPotentially compromised credentials for Google Cloud Platform/API project  \r\nMy Roport (id: my-roport)\r\n\r\n\r\n\r\nDear Customer,\r\n\r\n\r\nWe detected a publicly exposed secret for the following OAuth client  \r\nassociated with project 878341164164:\r\n\r\nSecret for client  \r\n878341164164-mm5q8t2kuk26dj44prkjvl1k27q15026.apps.googleusercontent.com  \r\nfound at the following URL:  \r\nhttps://github.com/NovosadovO/morning-report/blob/3984b4dc7231193fbaf225b40bf3c09d4fbaa2ff/monitor.py\r\n\r\nTo prevent potential security and abuse risks, you must take action in  \r\naccordance with our OAuth 2.0 Policies guidance to “handle client  \r\ncredentials securely”. Your client secret may have been inadvertently  \r\npublished in public sources or websites (for instance, the credentials were  \r\nmistakenly uploaded to a code repository). Please note that as the  \r\nproject/account owner, you are responsible for securing your client  \r\ncredentials.\r\n\r\n\r\n\r\nImmediate action is required to generate a new secret to continue using  \r\nOAuth. We strongly recommend that you take the following steps:\r\n\r\n\r\nLog in to the Google Cloud Console.\r\nGenerate a new client secret following these instructions.\r\nUpdate any applications or websites to use the new client secret\r\nTake immediate steps to ensure that your client secrets are not embedded in  \r\npublic source code systems, stored in download directories, or  \r\nunintentionally shared in other ways.\r\n\r\nThank you for ensuring that your Google OAuth clients are secure. Together  \r\nwe can make sure that you and your users are safe.\r\n\r\nSincerely,\r\n\r\nGoogle Cloud Platform Team\r\n\r\n\r\n\r\n\r\nGO TO MY CONSOLE\r\n\r\n\r\n\r\n\r\nSincerely,\r\n\r\nGoogle Cloud Platform Trust & Safety\r\n\r\n\r\n\r\n\r\nGoogle\r\n\r\n© 2016 Google Inc. 1600 Amphitheatre Parkway, Mountain View, CA 94043\r\n\r\nYou have received this mandatory service announcement to update you about  \r\nimportant changes to Google Cloud Platform or your account.\r\n\r\n\r\n\r\n\r\n"
  },
  "75208": {
    "subject": "Quick Hello from Runable!",
    "sender": "abhijeet@runable.com",
    "body": "Hi,\r\n\r\nI'm Abhijeet from team Runable. You're one of our most active users, and I\r\nwanted to reach out personally.\r\n\r\nWe're looking to feature a few people from our community, and before\r\nanything, I'd just love to connect and hear about your experience, what's\r\nworking for you, what's getting in your way, and how Runable has been for\r\nyou so far.\r\n\r\nWould you be open to a quick chat? Please select your preferred time slot:\r\nhttps://calendly.com/abhijeet-runable/30min\r\n\r\nThanks for being with us,\r\n\r\nAbhijeet\r\nTeam Runable\r\n"
  },
  "75204": {
    "subject": "Quick Hello from Runable!",
    "sender": "abhijeet@runable.com",
    "body": "Hi novosadovoleg@gmail.com\r\n\r\nI'm Abhijeet from team Runable. You're one of our most active users, and I\r\nwanted to reach out personally.\r\n\r\nWe're looking to feature a few people from our community, and before\r\nanything, I'd just love to connect and hear about your experience, what's\r\nworking for you, what's getting in your way, and how Runable has been for\r\nyou so far.\r\n\r\nWould you be open to a quick chat? Please select your preferred time slot:\r\nhttps://calendly.com/abhijeet-runable/30min\r\n\r\nThanks for being with us,\r\n\r\nAbhijeet\r\nTeam Runable\r\n"
  }
}