{
  "bitcoin": {
    "price": 64769,
    "ts": 1784836831
  },
  "ethereum": {
    "price": 1873.35,
    "ts": 1784836831
  },
  "binancecoin": {
    "price": 565.87,
    "ts": 1784836831
  },
  "ripple": {
    "price": 1.1,
    "ts": 1784836831
  },
  "solana": {
    "price": 75.66,
    "ts": 1784836831
  },
  "dogecoin": {
    "price": 0.069152,
    "ts": 1784836831
  },
  "cardano": {
    "price": 0.169401,
    "ts": 1784836831
  },
  "tron": {
    "price": 0.327,
    "ts": 1784836831
  },
  "chainlink": {
    "price": 8.44,
    "ts": 1784836831
  },
  "avalanche-2": {
    "price": 6.27,
    "ts": 1784836831
  },
  "the-open-network": {
    "price": 1.46,
    "ts": 1784836831
  },
  "stellar": {
    "price": 0.182579,
    "ts": 1784836831
  },
  "hedera-hashgraph": {
    "price": 0.072014,
    "ts": 1784836831
  },
  "sui": {
    "price": 0.744022,
    "ts": 1784836831
  },
  "bitcoin-cash": {
    "price": 209.74,
    "ts": 1784836831
  },
  "litecoin": {
    "price": 46.88,
    "ts": 1784836831
  },
  "polkadot": {
    "price": 0.814369,
    "ts": 1784836831
  },
  "hyperliquid": {
    "price": 57.92,
    "ts": 1784836831
  },
  "monero": {
    "price": 354.27,
    "ts": 1784836831
  },
  "ondo-finance": {
    "price": 0.400022,
    "ts": 1784836831
  }
}