{
  "bitcoin": {
    "price": 67016,
    "ts": 1780480831
  },
  "ethereum": {
    "price": 1875.31,
    "ts": 1780480831
  },
  "binancecoin": {
    "price": 641.24,
    "ts": 1780480831
  },
  "ripple": {
    "price": 1.24,
    "ts": 1780480831
  },
  "solana": {
    "price": 75.03,
    "ts": 1780480831
  },
  "dogecoin": {
    "price": 0.093859,
    "ts": 1780480831
  },
  "cardano": {
    "price": 0.216659,
    "ts": 1780480831
  },
  "tron": {
    "price": 0.332147,
    "ts": 1780480831
  },
  "chainlink": {
    "price": 8.51,
    "ts": 1780480831
  },
  "avalanche-2": {
    "price": 8.29,
    "ts": 1780480831
  },
  "the-open-network": {
    "price": 2.01,
    "ts": 1780480831
  },
  "stellar": {
    "price": 0.225778,
    "ts": 1780480831
  },
  "hedera-hashgraph": {
    "price": 0.087312,
    "ts": 1780480831
  },
  "sui": {
    "price": 0.83235,
    "ts": 1780480831
  },
  "bitcoin-cash": {
    "price": 248.87,
    "ts": 1780480831
  },
  "litecoin": {
    "price": 48.15,
    "ts": 1780480831
  },
  "polkadot": {
    "price": 1.11,
    "ts": 1780480831
  },
  "hyperliquid": {
    "price": 72.1,
    "ts": 1780480831
  },
  "monero": {
    "price": 337.8,
    "ts": 1780480831
  },
  "ondo-finance": {
    "price": 0.413214,
    "ts": 1780480831
  }
}