{
  "bitcoin": {
    "price": 58663,
    "ts": 1782853260
  },
  "ethereum": {
    "price": 1573.86,
    "ts": 1782853260
  },
  "binancecoin": {
    "price": 544.79,
    "ts": 1782853260
  },
  "ripple": {
    "price": 1.041,
    "ts": 1782853260
  },
  "solana": {
    "price": 73.58,
    "ts": 1782853260
  },
  "dogecoin": {
    "price": 0.071941,
    "ts": 1782853260
  },
  "cardano": {
    "price": 0.143583,
    "ts": 1782853260
  },
  "tron": {
    "price": 0.314725,
    "ts": 1782853260
  },
  "chainlink": {
    "price": 7.17,
    "ts": 1782853260
  },
  "avalanche-2": {
    "price": 6.54,
    "ts": 1782853260
  },
  "the-open-network": {
    "price": 1.54,
    "ts": 1782853260
  },
  "stellar": {
    "price": 0.182181,
    "ts": 1782853260
  },
  "hedera-hashgraph": {
    "price": 0.069087,
    "ts": 1782853260
  },
  "sui": {
    "price": 0.692011,
    "ts": 1782853260
  },
  "bitcoin-cash": {
    "price": 199.29,
    "ts": 1782853260
  },
  "litecoin": {
    "price": 41.65,
    "ts": 1782853260
  },
  "polkadot": {
    "price": 0.817131,
    "ts": 1782853260
  },
  "hyperliquid": {
    "price": 64.76,
    "ts": 1782853260
  },
  "monero": {
    "price": 305.99,
    "ts": 1782853260
  },
  "ondo-finance": {
    "price": 0.310061,
    "ts": 1782853260
  }
}