{
  "bitcoin": {
    "price": 63360,
    "ts": 1781964012
  },
  "ethereum": {
    "price": 1716.84,
    "ts": 1781964012
  },
  "binancecoin": {
    "price": 583.77,
    "ts": 1781964012
  },
  "ripple": {
    "price": 1.14,
    "ts": 1781964012
  },
  "solana": {
    "price": 71.14,
    "ts": 1781964012
  },
  "dogecoin": {
    "price": 0.08325,
    "ts": 1781964012
  },
  "cardano": {
    "price": 0.161322,
    "ts": 1781964012
  },
  "tron": {
    "price": 0.325803,
    "ts": 1781964012
  },
  "chainlink": {
    "price": 7.88,
    "ts": 1781964012
  },
  "avalanche-2": {
    "price": 6.12,
    "ts": 1781964012
  },
  "the-open-network": {
    "price": 1.62,
    "ts": 1781964012
  },
  "stellar": {
    "price": 0.213375,
    "ts": 1781964012
  },
  "hedera-hashgraph": {
    "price": 0.079781,
    "ts": 1781964012
  },
  "sui": {
    "price": 0.710134,
    "ts": 1781964012
  },
  "bitcoin-cash": {
    "price": 197.32,
    "ts": 1781964012
  },
  "litecoin": {
    "price": 44.06,
    "ts": 1781964012
  },
  "polkadot": {
    "price": 0.9578,
    "ts": 1781964012
  },
  "hyperliquid": {
    "price": 69.63,
    "ts": 1781964012
  },
  "monero": {
    "price": 315.29,
    "ts": 1781964012
  },
  "ondo-finance": {
    "price": 0.343489,
    "ts": 1781964012
  }
}